adafruit_ft5336.py
adafruit_circuitpython_ft5336-1.1.6.dist-info/licenses/LICENSE
adafruit_circuitpython_ft5336-1.1.6.dist-info/METADATA
adafruit_circuitpython_ft5336-1.1.6.dist-info/WHEEL
adafruit_circuitpython_ft5336-1.1.6.dist-info/top_level.txt
adafruit_circuitpython_ft5336-1.1.6.dist-info/RECORD
